[
  {
    "name": "Javascript",
    "icon": "javascript.png"
  },
  {
    "name": "React",
    "icon": "react.png"
  },
  {
    "name": "Git",
    "icon": "github.png"
  },
  {
    "name": "Firebase",
    "icon": "firebase.png"
  },
  {
    "name": "CSS",
    "icon": "css.png"
  },
  {
    "name": "Sass",
    "icon": "sass.png"
  },
  {
    "name": "TBD",
    "icon": "no-icon.png"
  },
  {
    "name": "TBD",
    "icon": "no-icon.png"
  },
  {
    "name": "TBD",
    "icon": "no-icon.png"
  },
  {
    "name": "TBD",
    "icon": "no-icon.png"
  }
]
